{
  "annotations": {
    "list": [
      {
        "builtIn": 1,
        "datasource": { "type": "grafana", "uid": "-- Grafana --" },
        "enable": true,
        "hide": true,
        "iconColor": "rgba(0, 211, 255, 1)",
        "name": "Annotations & Alerts",
        "type": "dashboard"
      }
    ]
  },
  "editable": true,
  "fiscalYearStartMonth": 0,
  "graphTooltip": 1,
  "id": null,
  "links": [],
  "panels": [
    {
      "datasource": { "type": "prometheus" },
      "fieldConfig": {
        "defaults": {
          "thresholds": {
            "mode": "absolute",
            "steps": [
              { "color": "green", "value": null },
              { "color": "orange", "value": 1 },
              { "color": "red", "value": 3 }
            ]
          }
        },
        "overrides": []
      },
      "gridPos": { "h": 4, "w": 6, "x": 0, "y": 0 },
      "id": 1,
      "options": {
        "colorMode": "background",
        "graphMode": "area",
        "justifyMode": "auto",
        "reduceOptions": { "calcs": ["lastNotNull"], "fields": "", "values": false },
        "textMode": "auto"
      },
      "title": "Currently Running Backups",
      "type": "stat",
      "targets": [
        {
          "datasource": { "type": "prometheus" },
          "expr": "sum(kopia_backups_count{job=\"hathi-backups\"}) or vector(0)",
          "legendFormat": "Running",
          "refId": "A"
        }
      ]
    },
    {
      "datasource": { "type": "prometheus" },
      "fieldConfig": {
        "defaults": {
          "custom": {
            "align": "auto",
            "cellOptions": { "type": "auto" },
            "inspect": false
          }
        },
        "overrides": [
          {
            "matcher": { "id": "byName", "options": "Time Since" },
            "properties": [
              { "id": "unit", "value": "s" },
              {
                "id": "thresholds",
                "value": {
                  "mode": "absolute",
                  "steps": [
                    { "color": "green", "value": null },
                    { "color": "orange", "value": 90000 },
                    { "color": "red", "value": 172800 }
                  ]
                }
              },
              {
                "id": "custom.cellOptions",
                "value": { "mode": "basic", "type": "color-background" }
              }
            ]
          },
          {
            "matcher": { "id": "byName", "options": "Last Backup" },
            "properties": [
              { "id": "unit", "value": "dateTimeFromNow" }
            ]
          }
        ]
      },
      "gridPos": { "h": 8, "w": 18, "x": 6, "y": 0 },
      "id": 2,
      "options": {
        "showHeader": true,
        "sortBy": [{ "desc": true, "displayName": "Time Since" }]
      },
      "title": "Last Backup Per Path",
      "type": "table",
      "targets": [
        {
          "datasource": { "type": "prometheus" },
          "expr": "kopia_backups_total{job=\"hathi-backups\"}",
          "format": "table",
          "instant": true,
          "legendFormat": "",
          "refId": "A"
        }
      ],
      "transformations": [
        {
          "id": "organize",
          "options": {
            "excludeByName": { "__name__": true, "job": true },
            "renameByName": { "instance": "Path", "Value": "Last Backup" }
          }
        },
        {
          "id": "calculateField",
          "options": {
            "alias": "Time Since",
            "mode": "reduceRow",
            "reduce": { "reducer": "lastNotNull" }
          }
        }
      ]
    },
    {
      "datasource": { "type": "prometheus" },
      "fieldConfig": {
        "defaults": {
          "color": { "mode": "palette-classic" },
          "custom": {
            "axisBorderShow": false,
            "axisLabel": "",
            "axisPlacement": "auto",
            "drawStyle": "line",
            "fillOpacity": 30,
            "lineInterpolation": "stepAfter",
            "lineWidth": 2,
            "pointSize": 5,
            "showPoints": "never",
            "spanNulls": false,
            "stacking": { "group": "A", "mode": "none" }
          }
        },
        "overrides": []
      },
      "gridPos": { "h": 8, "w": 24, "x": 0, "y": 8 },
      "id": 3,
      "options": {
        "legend": { "calcs": [], "displayMode": "list", "placement": "bottom" },
        "tooltip": { "mode": "multi", "sort": "desc" }
      },
      "title": "Backup Activity",
      "type": "timeseries",
      "targets": [
        {
          "datasource": { "type": "prometheus" },
          "expr": "kopia_backups_count{job=\"hathi-backups\"}",
          "legendFormat": "{{instance}} ({{stage}})",
          "refId": "A"
        }
      ]
    },
    {
      "datasource": { "type": "prometheus" },
      "fieldConfig": {
        "defaults": {
          "color": { "mode": "palette-classic" },
          "custom": {
            "axisBorderShow": false,
            "axisLabel": "",
            "axisPlacement": "auto",
            "drawStyle": "points",
            "fillOpacity": 0,
            "lineInterpolation": "linear",
            "lineWidth": 1,
            "pointSize": 8,
            "showPoints": "always",
            "spanNulls": false,
            "stacking": { "group": "A", "mode": "none" }
          },
          "unit": "dateTimeAsIso"
        },
        "overrides": []
      },
      "gridPos": { "h": 8, "w": 24, "x": 0, "y": 16 },
      "id": 4,
      "options": {
        "legend": { "calcs": ["lastNotNull"], "displayMode": "table", "placement": "bottom" },
        "tooltip": { "mode": "multi", "sort": "desc" }
      },
      "title": "Last Backup Timestamps",
      "type": "timeseries",
      "targets": [
        {
          "datasource": { "type": "prometheus" },
          "expr": "kopia_backups_total{job=\"hathi-backups\"} * 1000",
          "legendFormat": "{{instance}}",
          "refId": "A"
        }
      ]
    }
  ],
  "schemaVersion": 39,
  "tags": ["backups", "kopia"],
  "templating": { "list": [] },
  "time": { "from": "now-7d", "to": "now" },
  "timepicker": {},
  "timezone": "",
  "title": "Backup Status",
  "uid": "backups",
  "version": 1
}